rasam/__init__.py
rasam/components/regex.py
rasam/components/url.py
rasam/decorators.py
rasam/importers/placeholder.py
rasam-0.5.2.dist-info/LICENSE
rasam-0.5.2.dist-info/WHEEL
rasam-0.5.2.dist-info/METADATA
rasam-0.5.2.dist-info/RECORD
