Metadata-Version: 2.1
Name: rasam
Version: 0.5.2
Summary: Rasa Improved
Home-page: https://github.com/roniemartinez/rasam
License: MIT
Keywords: URL extractor for Rasa,Regex entity extractor for Rasa,Placeholder importer for Rasa
Author: Ronie Martinez
Author-email: ronmarti18@gmail.com
Requires-Python: >=3.7,<3.9
Classifier: Development Status :: 3 - Alpha
Classifier: License :: OSI Approved :: MIT License
Classifier: Programming Language :: Python :: 3
Classifier: Programming Language :: Python :: 3.7
Classifier: Programming Language :: Python :: 3.8
Classifier: Programming Language :: Python :: Implementation :: CPython
Requires-Dist: Faker (>=8.1.4,<14.0.0)
Requires-Dist: rasa (>=2.8.12,<3.0.0)
Requires-Dist: urlextract (>=1.2.0,<2.0.0)
Project-URL: Donate, https://github.com/sponsors/roniemartinez
Project-URL: Repository, https://github.com/roniemartinez/rasam
